[
	{
		"id": 1,
		"name": "Brandon Pfeffer",
		"image": "http://loremflickr.com/640/480/transport",
		"price": 557.00,
		"like": 18,
		"is_like": true
	},
	{
		"id": 2,
		"name": "Darrin Von",
		"image": "http://loremflickr.com/640/480/city",
		"price": 84.00,
		"like": 86,
		"is_like": false
	},
	{
		"id": 3,
		"name": "Robin Miller",
		"image": "http://loremflickr.com/640/480/transport",
		"price": 627.00,
		"like": 52,
		"is_like": false
	},
	{
		"id": 4,
		"name": "Winifred Pfeffer IV",
		"image": "http://loremflickr.com/640/480/animals",
		"price": 686.00,
		"like": 14,
		"is_like": true
	},
	{
		"id": 5,
		"name": "Bobbie West",
		"image": "http://loremflickr.com/640/480/nightlife",
		"price": 872.00,
		"like": 23,
		"is_like": true
	},
	{
		"id": 6,
		"name": "Juana Reichert",
		"image": "http://loremflickr.com/640/480/fashion",
		"price": 166.00,
		"like": 72,
		"is_like": false
	},
	{
		"id": 7,
		"name": "Mabel Maggio",
		"image": "http://loremflickr.com/640/480/people",
		"price": 79.00,
		"like": 26,
		"is_like": false
	},
	{
		"id": 8,
		"name": "Salvador Klein",
		"image": "http://loremflickr.com/640/480/technics",
		"price": 834.00,
		"like": 11,
		"is_like": true
	},
	{
		"id": 9,
		"name": "Abel Nolan",
		"image": "http://loremflickr.com/640/480/abstract",
		"price": 73.00,
		"like": 71,
		"is_like": false
	},
	{
		"id": 10,
		"name": "Ms. Floyd Medhurst",
		"image": "http://loremflickr.com/640/480/technics",
		"price": 645.00,
		"like": 92,
		"is_like": true
	},
	{
		"id": 11,
		"name": "Marcus Bins",
		"image": "http://loremflickr.com/640/480/food",
		"price": 594.00,
		"like": 79,
		"is_like": false
	},
	{
		"id": 12,
		"name": "Salvador Goodwin",
		"image": "http://loremflickr.com/640/480/abstract",
		"price": 706.00,
		"like": 92,
		"is_like": true
	},
	{
		"id": 13,
		"name": "Stacey Schimmel",
		"image": "http://loremflickr.com/640/480/nature",
		"price": 113.00,
		"like": 32,
		"is_like": false
	},
	{
		"id": 14,
		"name": "Alicia Harris",
		"image": "http://loremflickr.com/640/480/people",
		"price": 966.00,
		"like": 17,
		"is_like": false
	},
	{
		"id": 15,
		"name": "Rochelle Glover II",
		"image": "http://loremflickr.com/640/480/people",
		"price": 235.00,
		"like": 11,
		"is_like": true
	},
	{
		"id": 16,
		"name": "Lana Bode PhD",
		"image": "http://loremflickr.com/640/480/abstract",
		"price": 570.00,
		"like": 14,
		"is_like": true
	},
	{
		"id": 17,
		"name": "Ella Macejkovic",
		"image": "http://loremflickr.com/640/480/technics",
		"price": 546.00,
		"like": 47,
		"is_like": true
	},
	{
		"id": 18,
		"name": "Martin Wolf",
		"image": "http://loremflickr.com/640/480/fashion",
		"price": 432.00,
		"like": 85,
		"is_like": false
	},
	{
		"id": 19,
		"name": "Johanna Schultz",
		"image": "http://loremflickr.com/640/480/technics",
		"price": 466.00,
		"like": 23,
		"is_like": false
	},
	{
		"id": 20,
		"name": "Candace Hoeger",
		"image": "http://loremflickr.com/640/480/nature",
		"price": 531.00,
		"like": 53,
		"is_like": true
	}
]